porpoise.py
setup.py
Porpoise.egg-info/PKG-INFO
Porpoise.egg-info/SOURCES.txt
Porpoise.egg-info/dependency_links.txt
Porpoise.egg-info/requires.txt
Porpoise.egg-info/top_level.txt
Porpoise.egg-info/zip-safe