Metadata-Version: 1.0
Name: Porpoise
Version: 0.1.0
Summary: A Redis-based analytics framework.
Home-page: https://github.com/alecthomas/porpoise
Author: Alec Thomas
Author-email: alec@swapoff.org
License: BSD
Platform: any
